new11/__init__.py
new11/line.py
new11-1.3.dist-info/METADATA
new11-1.3.dist-info/WHEEL
new11-1.3.dist-info/entry_points.txt
new11-1.3.dist-info/top_level.txt
new11-1.3.dist-info/RECORD
